CHANGELOG.txt
LICENCE.txt
MANIFEST.in
README.txt
setup.py
numpy1/__init__.py
numpy1.egg-info/PKG-INFO
numpy1.egg-info/SOURCES.txt
numpy1.egg-info/dependency_links.txt
numpy1.egg-info/top_level.txt