Metadata-Version: 1.1
Name: numpy1
Version: 0.0.1
Summary: Python
Home-page: UNKNOWN
Author: python
Author-email: aba@ganl.com
License: MIT
Keywords: Python
Platform: UNKNOWN
Classifier: Development Status :: 5 - Production/Stable
Classifier: Intended Audience :: Education
Classifier: Operating System :: Microsoft :: Windows :: Windows 10
Classifier: License :: OSI Approved :: MIT License
Classifier: Programming Language :: Python :: 3
